irbench/__init__.py
irbench/irbench.py
irbench/evals/__init__.py
irbench/evals/eval_helper.py
irbench/evals/evaluate.py
irbench/irsys/__init__.py
irbench/irsys/feature_store.py
irbench/irsys/global_descriptor.py
irbench/irsys/local_descriptor.py
irbench/utils/__init__.py
irbench/utils/utils.py
irbench_vision-0.1.12.dist-info/METADATA
irbench_vision-0.1.12.dist-info/WHEEL
irbench_vision-0.1.12.dist-info/top_level.txt
irbench_vision-0.1.12.dist-info/RECORD
