Metadata-Version: 2.1
Name: irbench-vision
Version: 0.1.12
Summary: Image Retrieval Performance Benchmark on Large-scale Dataset
Home-page: UNKNOWN
Author: Minchul Shin
Author-email: min.nashory@navercorp.com
License: MIT
Platform: UNKNOWN
